xaal/__init__.py
xaal/aqara/__init__.py
xaal/aqara/__main__.py
xaal/aqara/devices.py
xaal/aqara/gw.py
xaal/aqara/network.py
xaal_aqara-0.2.2.dist-info/METADATA
xaal_aqara-0.2.2.dist-info/WHEEL
xaal_aqara-0.2.2.dist-info/top_level.txt
xaal_aqara-0.2.2.dist-info/RECORD
